[{"country": "Afghanistan", "code": "AFG", "population": "32.358"}, {"country": "Albania", "code": "ALB", "population": "3.216"}, {"country": "Algeria", "code": "DZA", "population": "35.980"}, {"country": "American Samoa", "code": "ASM", "population": "70"}, {"country": "Andorra", "code": "AND", "population": "86"}, {"country": "Angola", "code": "AGO", "population": "19.618"}, {"country": "Anguilla", "code": "AIA", "population": "16"}, {"country": "Antigua and Barbuda", "code": "ATG", "population": "90"}, {"country": "Argentina", "code": "ARG", "population": "40.765"}, {"country": "Armenia", "code": "ARM", "population": "3.100"}, {"country": "Aruba", "code": "ABW", "population": "108"}, {"country": "Australia", "code": "AUS", "population": "22.606"}, {"country": "Austria", "code": "AUT", "population": "8.413"}, {"country": "Azerbaijan", "code": "AZE", "population": "9.306"}, {"country": "Bahamas", "code": "BHS", "population": "347"}, {"country": "Bahrain", "code": "BHR", "population": "1.324"}, {"country": "Bangladesh", "code": "BGD", "population": "150.494"}, {"country": "Barbados", "code": "BRB", "population": "274"}, {"country": "Belarus", "code": "BLR", "population": "9.559"}, {"country": "Belgium", "code": "BEL", "population": "10.754"}, {"country": "Belize", "code": "BLZ", "population": "318"}, {"country": "Benin", "code": "BEN", "population": "9.100"}, {"country": "Bermuda", "code": "BMU", "population": "65"}, {"country": "Bhutan", "code": "BTN", "population": "738"}, {"country": "Bolivia", "code": "BOL", "population": "10.088"}, {"country": "Bosnia and Herzegovina", "code": "BIH", "population": "3.752"}, {"country": "Botswana", "code": "BWA", "population": "2.031"}, {"country": "Brazil", "code": "BVT", "population": "196.655"}, {"country": "British Virgin Islands", "code": "BRA", "population": "23"}, {"country": "Brunei", "code": "IOT", "population": "406"}, {"country": "Bulgaria", "code": "BRN", "population": "7.446"}, {"country": "Burkina Faso", "code": "BGR", "population": "16.968"}, {"country": "Burundi", "code": "BFA", "population": "8.575"}, {"country": "Cambodia", "code": "BDI", "population": "14.305"}, {"country": "Cameroon", "code": "KHM", "population": "20.030"}, {"country": "Canada", "code": "CMR", "population": "34.350"}, {"country": "Cape Verde", "code": "CAN", "population": "501"}, {"country": "Cayman Islands", "code": "CPV", "population": "57"}, {"country": "Central African Republic", "code": "CYM", "population": "4.487"}, {"country": "Chad", "code": "CAF", "population": "11.525"}, {"country": "Channel Islands", "code": "TCD", "population": "154"}, {"country": "Chile", "code": "CHL", "population": "17.270"}, {"country": "China", "code": "CHN", "population": "1.347.565"}, {"country": "Colombia", "code": "COL", "population": "46.927"}, {"country": "Comoros", "code": "COM", "population": "754"}, {"country": "Congo", "code": "COG", "population": "4.140"}, {"country": "Congo Dem Rep", "code": "COD", "population": "67.758"}, {"country": "Cook Islands", "code": "COK", "population": "20"}, {"country": "Costa Rica", "code": "CRI", "population": "4.727"}, {"country": "Cªte d'Ivoire", "code": "CIV", "population": "20.153"}, {"country": "Croatia", "code": "HRV", "population": "4.396"}, {"country": "Cuba", "code": "CUB", "population": "11.254"}, {"country": "Cyprus", "code": "CYP", "population": "1.117"}, {"country": "Czech Republic", "code": "CZE", "population": "10.534"}, {"country": "Denmark", "code": "DNK", "population": "5.573"}, {"country": "Djibouti", "code": "DJI", "population": "906"}, {"country": "Dominica", "code": "DMA", "population": "68"}, {"country": "Dominican Republic", "code": "DOM", "population": "10.056"}, {"country": "Ecuador", "code": "ECU", "population": "14.666"}, {"country": "Egypt", "code": "EGY", "population": "82.537"}, {"country": "El Salvador", "code": "SLV", "population": "6.227"}, {"country": "Equatorial Guinea", "code": "GNQ", "population": "720"}, {"country": "Eritrea", "code": "ERI", "population": "5.415"}, {"country": "Estonia", "code": "EST", "population": "1.341"}, {"country": "Ethiopia", "code": "ETH", "population": "84.734"}, {"country": "Faeroe Islands", "code": "FRO", "population": "49"}, {"country": "Falkland Islands (Malvinas)", "code": "FLK", "population": "3"}, {"country": "Fiji", "code": "FJI", "population": "868"}, {"country": "Finland", "code": "FIN", "population": "5.385"}, {"country": "France", "code": "FRA", "population": "63.126"}, {"country": "French Guiana", "code": "GUF", "population": "237"}, {"country": "French Polynesia", "code": "PYF", "population": "274"}, {"country": "Gabon", "code": "GAB", "population": "1.534"}, {"country": "Gambia", "code": "GMB", "population": "1.776"}, {"country": "Georgia", "code": "GEO", "population": "4.329"}, {"country": "Germany", "code": "DEU", "population": "82.163"}, {"country": "Ghana", "code": "GHA", "population": "24.966"}, {"country": "Gibraltar", "code": "GIB", "population": "29"}, {"country": "Greece", "code": "GRC", "population": "11.390"}, {"country": "Greenland", "code": "GRL", "population": "57"}, {"country": "Grenada", "code": "GRD", "population": "105"}, {"country": "Guadeloupe", "code": "GLP", "population": "463"}, {"country": "Guam", "code": "GUM", "population": "182"}, {"country": "Guatemala", "code": "GTM", "population": "14.757"}, {"country": "Guinea", "code": "GIN", "population": "10.222"}, {"country": "Guinea-Bissau", "code": "GNB", "population": "1.547"}, {"country": "Guyana", "code": "GUY", "population": "756"}, {"country": "Haiti", "code": "HTI", "population": "10.124"}, {"country": "Honduras", "code": "HND", "population": "7.755"}, {"country": "Hong Kong", "code": "HKG", "population": "7.122"}, {"country": "Hungary", "code": "HUN", "population": "9.966"}, {"country": "Iceland", "code": "ISL", "population": "324"}, {"country": "India", "code": "IND", "population": "1.241.492"}, {"country": "Indonesia", "code": "IDN", "population": "242.326"}, {"country": "Iran", "code": "IRN", "population": "74.799"}, {"country": "Iraq", "code": "IRQ", "population": "32.665"}, {"country": "Ireland", "code": "IRL", "population": "4.526"}, {"country": "Isle of Man", "code": "IMN", "population": "83"}, {"country": "Israel", "code": "ISR", "population": "7.562"}, {"country": "Italy", "code": "ITA", "population": "60.789"}, {"country": "Jamaica", "code": "JAM", "population": "2.751"}, {"country": "Japan", "code": "JPN", "population": "126.497"}, {"country": "Jordan", "code": "JOR", "population": "6.330"}, {"country": "Kazakhstan", "code": "KAZ", "population": "16.207"}, {"country": "Kenya", "code": "KEN", "population": "41.610"}, {"country": "Kiribati", "code": "KIR", "population": "101"}, {"country": "Korea North", "code": "PRK", "population": "24.451"}, {"country": "Korea South", "code": "KOR", "population": "48.391"}, {"country": "Kuwait", "code": "KWT", "population": "2.818"}, {"country": "Kyrgyzstan", "code": "KGZ", "population": "5.393"}, {"country": "Laos", "code": "LAO", "population": "6.288"}, {"country": "Latvia", "code": "LVA", "population": "2.243"}, {"country": "Lebanon", "code": "LBN", "population": "4.259"}, {"country": "Lesotho", "code": "LSO", "population": "2.194"}, {"country": "Liberia", "code": "LBR", "population": "4.129"}, {"country": "Libya", "code": "LBY", "population": "6.423"}, {"country": "Liechtenstein", "code": "LIE", "population": "36"}, {"country": "Lithuania", "code": "LTU", "population": "3.307"}, {"country": "Luxembourg", "code": "LUX", "population": "516"}, {"country": "Macao", "code": "MAC", "population": "556"}, {"country": "Macedonia", "code": "MKD", "population": "2.064"}, {"country": "Madagascar", "code": "MDG", "population": "21.315"}, {"country": "Malawi", "code": "MWI", "population": "15.381"}, {"country": "Malaysia", "code": "MYS", "population": "28.859"}, {"country": "Maldives", "code": "MDV", "population": "320"}, {"country": "Mali", "code": "MLI", "population": "15.840"}, {"country": "Malta", "code": "MLT", "population": "418"}, {"country": "Marshall Islands", "code": "MHL", "population": "55"}, {"country": "Martinique", "code": "MTQ", "population": "407"}, {"country": "Mauritania", "code": "MRT", "population": "3.542"}, {"country": "Mauritius", "code": "MUS", "population": "1.307"}, {"country": "Mayotte", "code": "MYT", "population": "211"}, {"country": "Mexico", "code": "MEX", "population": "114.793"}, {"country": "Micronesia", "code": "FSM", "population": "112"}, {"country": "Moldova", "code": "MDA", "population": "3.545"}, {"country": "Monaco", "code": "MCO", "population": "35"}, {"country": "Mongolia", "code": "MNG", "population": "2.800"}, {"country": "Montenegro", "code": "MNE", "population": "632"}, {"country": "Montserrat", "code": "MSR", "population": "6"}, {"country": "Morocco", "code": "MAR", "population": "32.273"}, {"country": "Mozambique", "code": "MOZ", "population": "23.930"}, {"country": "Myanmar", "code": "MMR", "population": "48.337"}, {"country": "Namibia", "code": "NAM", "population": "2.324"}, {"country": "Nauru", "code": "NRU", "population": "10"}, {"country": "Nepal", "code": "NPL", "population": "30.486"}, {"country": "Netherlands", "code": "NLD", "population": "16.665"}, {"country": "Netherlands Antilles", "code": "NCL", "population": "203"}, {"country": "New Caledonia", "code": "NZL", "population": "255"}, {"country": "New Zealand", "code": "NIC", "population": "4.415"}, {"country": "Nicaragua", "code": "NER", "population": "5.870"}, {"country": "Niger", "code": "NGA", "population": "16.069"}, {"country": "Nigeria", "code": "NIU", "population": "162.471"}, {"country": "Niue", "code": "NFK", "population": "1"}, {"country": "Northern Mariana Islands", "code": "MNP", "population": "61"}, {"country": "Norway", "code": "NOR", "population": "4.925"}, {"country": "Oman", "code": "OMN", "population": "2.846"}, {"country": "Pakistan", "code": "PAK", "population": "176.745"}, {"country": "Palau", "code": "PLW", "population": "21"}, {"country": "Palestinian Territory", "code": " Occupied", "population": "PSE"}, {"country": "Panama", "code": "PAN", "population": "3.571"}, {"country": "Papua New Guinea", "code": "PNG", "population": "7.014"}, {"country": "Paraguay", "code": "PRY", "population": "6.568"}, {"country": "Peru", "code": "PER", "population": "29.400"}, {"country": "Philippines", "code": "PHL", "population": "94.852"}, {"country": "Poland", "code": "PCN", "population": "38.299"}, {"country": "Portugal", "code": "POL", "population": "10.690"}, {"country": "Puerto Rico", "code": "PRT", "population": "3.746"}, {"country": "Qatar", "code": "PRI", "population": "1.870"}, {"country": "R_union", "code": "QAT", "population": "856"}, {"country": "Romania", "code": "ROU", "population": "21.436"}, {"country": "Russia", "code": "RUS", "population": "142.836"}, {"country": "Rwanda", "code": "RWA", "population": "10.943"}, {"country": "Saint Helena", "code": "SHN", "population": "4"}, {"country": "Saint Kitts and Nevis", "code": "KNA", "population": "53"}, {"country": "Saint Lucia", "code": "LCA", "population": "176"}, {"country": "Saint Pierre and Miquelon", "code": "SPM", "population": "6"}, {"country": "Saint Vincent and the Grenadines", "code": "VCT", "population": "109"}, {"country": "Samoa", "code": "WSM", "population": "184"}, {"country": "San Marino", "code": "SMR", "population": "32"}, {"country": "Sao Tome and Principe", "code": "STP", "population": "169"}, {"country": "Saudi Arabia", "code": "SAU", "population": "28.083"}, {"country": "Senegal", "code": "SEN", "population": "12.768"}, {"country": "Serbia", "code": "SRB", "population": "9.854"}, {"country": "Seychelles", "code": "SYC", "population": "87"}, {"country": "Sierra Leone", "code": "SLE", "population": "5.997"}, {"country": "Singapore", "code": "SGP", "population": "5.188"}, {"country": "Slovakia", "code": "SVK", "population": "5.472"}, {"country": "Slovenia", "code": "SVN", "population": "2.035"}, {"country": "Solomon Islands", "code": "SLB", "population": "552"}, {"country": "Somalia", "code": "SOM", "population": "9.557"}, {"country": "South Africa", "code": "ZAF", "population": "50.460"}, {"country": "Spain", "code": "ESP", "population": "46.455"}, {"country": "Sri Lanka", "code": "LKA", "population": "21.045"}, {"country": "Sudan", "code": "SDN", "population": "44.632"}, {"country": "Suriname", "code": "SUR", "population": "529"}, {"country": "Swaziland", "code": "SWZ", "population": "1.203"}, {"country": "Sweden", "code": "SWE", "population": "9.441"}, {"country": "Switzerland", "code": "CHE", "population": "7.702"}, {"country": "Syria", "code": "SYR", "population": "20.766"}, {"country": "Tajikistan", "code": "TJK", "population": "6.977"}, {"country": "Tanzania", "code": "TZA", "population": "46.218"}, {"country": "Thailand", "code": "THA", "population": "69.519"}, {"country": "Timor-Leste", "code": "TLS", "population": "1.154"}, {"country": "Togo", "code": "TGO", "population": "6.155"}, {"country": "Tokelau", "code": "TKL", "population": "1"}, {"country": "Tonga", "code": "TON", "population": "105"}, {"country": "Trinidad and Tobago", "code": "TTO", "population": "1.346"}, {"country": "Tunisia", "code": "TUN", "population": "10.594"}, {"country": "Turkey", "code": "TUR", "population": "73.640"}, {"country": "Turkmenistan", "code": "TKM", "population": "5.105"}, {"country": "Turks and Caicos Islands", "code": "TCA", "population": "39"}, {"country": "Tuvalu", "code": "TUV", "population": "10"}, {"country": "Uganda", "code": "UGA", "population": "34.509"}, {"country": "Ukraine", "code": "UKR", "population": "45.190"}, {"country": "United Arab Emirates", "code": "ARE", "population": "7.891"}, {"country": "United Kingdom", "code": "GBR", "population": "62.417"}, {"country": "United States", "code": "USA", "population": "313.085"}, {"country": "United States Virgin Islands", "code": "VIR", "population": "109"}, {"country": "Uruguay", "code": "URY", "population": "3.380"}, {"country": "Uzbekistan", "code": "UZB", "population": "27.760"}, {"country": "Vanuatu", "code": "VUT", "population": "246"}, {"country": "Vatican City", "code": "VEN", "population": "0"}, {"country": "Venezuela", "code": "VNM", "population": "29.437"}, {"country": "Vietnam", "code": "VGB", "population": "88.792"}, {"country": "Wallis and Futuna Islands", "code": "WLF", "population": "13"}, {"country": "Western Sahara", "code": "ESH", "population": "548"}, {"country": "Yemen", "code": "YEM", "population": "24.800"}, {"country": "Zambia", "code": "ZMB", "population": "13.475"}, {"country": "Zimbabwe", "code": "ZWE", "population": "12.754"}]